BCNN.v
module BCNN (
    clk_in,
    reset_in,
    data_in,
    weight_in,
    bias_in,
    data_out
);
input              clk_in, reset_in;
input        [8:0] data_in;
input        [8:0] weight_in;
input        [3:0] bias_in; // -8 <= bias_in <= 7
output reg         data_out;

reg                binarized_out;
reg                partial_product  [0:8];
reg          [3:0] population_count;
reg          [4:0] true_sum;

integer i;
always @(*) begin
    for (i = 0; i < 9; i = i + 1) begin
        partial_product[i] = data_in[i] ~^ weight_in[i];
    end
end

always @(*) begin
    population_count = partial_product[0] +
                       partial_product[1] +
                       partial_product[2] +
                       partial_product[3] +
                       partial_product[4] +
                       partial_product[5] +
                       partial_product[6] +
                       partial_product[7] +
                       partial_product[8];    
end

//如果bias在這直接做，加速器跟CPU之間要傳輸的bit直接變1/5
always @(*) begin
    true_sum = 2 * population_count - 5'd9 + {bias_in[3], bias_in};
    if (true_sum[4] == 1'b1) begin
        binarized_out = 0;
    end
    else begin
        binarized_out = 1;
    end
end

always @(posedge clk_in or negedge reset_in) begin
    if (reset_in == 1'b0) begin
        data_out <= 1'b0;
    end
    else begin
        data_out <= binarized_out;
    end
end
endmodule

BCNN_tb.v
`timescale 1ns/10ps
`define CYCLE    10           	      // Modify your clock period here
`define SDFFILE    "./BCNN_tb.sdf"    // Modify your sdf file name
`define DATA       "./data.dat"       // Modify your test image file
`define WEIGHT     "./weight.dat"     // Modify your test image file
`define BIAS       "./bias.dat"       // Modify your test bias file
`define EXPECT     "./output.dat"     // Modify your output golden file

module BCNN_tb;

parameter DATA_LENGTH   = 100;

reg           clk;
reg           reset;
reg   [8:0]   data_in,weight_in;
reg   [3:0]   bias_in;
wire          data_out;

reg   [3:0]   bias_mem    [0:DATA_LENGTH-1];
reg           out_mem     [0:DATA_LENGTH-1];
reg   [8:0]   data_mem    [0:DATA_LENGTH-1];
reg   [8:0]   weight_mem  [0:DATA_LENGTH-1];

reg           stop;
integer       i, out_file, err;

BCNN BCNN( .clk_in(clk),
           .reset_in(reset),
           .data_in(data_in),
           .weight_in(weight_in),
           .bias_in(bias_in),
           .data_out(data_out) );       

`ifdef SDF
initial $sdf_annotate(`SDFFILE, BCNN);
`endif   

initial	$readmemb (`DATA,    data_mem);
initial	$readmemb (`WEIGHT,  weight_mem);
initial	$readmemb (`BIAS,    bias_mem);
initial	$readmemb (`EXPECT,  out_mem);

initial begin
    clk         = 1'b1;
    reset       = 1'b1;
    stop        = 1'b0;
    err         = 0;
    i           = 0;   
    
    #2.5 reset=1'b0;                            // system reset
    #2.5 reset=1'b1;
end

always begin #(`CYCLE/2) clk = ~clk; end

initial begin
	$dumpfile("BCNN.vcd");
	$dumpvars;

   out_file = $fopen("out.dat");
   if (out_file == 0) begin
        $display("Output file open error !");
        $finish;
   end
end


always @(negedge clk)begin
    if(i < DATA_LENGTH) begin
        bias_in   = bias_mem[i];
        data_in   = data_mem[i];
        weight_in = weight_mem[i];
    end
	i = i+1;
end

always @(posedge clk)begin
    if (i == DATA_LENGTH + 1) begin
        stop = 1'b1;
    end
    #(0.2*`CYCLE);
    if (i > 0) begin
        $fdisplay(out_file,"%b", data_out);
        if(data_out !== out_mem[i-1]) begin
            $display("ERROR at %d:output %h !=expect %h ",i-1, data_out, out_mem[i-1]);
            err = err + 1;
        end
    end
end

initial begin
    @(posedge stop)
    $display("---------------------------------------------\n");
    if (err == 0)  begin
    $display("All data have been generated successfully!\n");
    $display("-------------------GOOD-------------------\n");
    end
    else begin
    $display("There are %d errors!\n", err);
    $display("-------------------BAD--------------------\n");
    end
    $fclose(out_file);
    $finish;
end
   
endmodule

BCNN.vcd
$date
	Mon Mar 20 15:20:17 2023
$end
$version
	Icarus Verilog
$end
$timescale
	10ps
$end
$scope module BCNN_tb $end
$var wire 1 ! data_out $end
$var reg 4 " bias_in [3:0] $end
$var reg 1 # clk $end
$var reg 9 $ data_in [8:0] $end
$var reg 1 % reset $end
$var reg 1 & stop $end
$var reg 9 ' weight_in [8:0] $end
$var integer 32 ( err [31:0] $end
$var integer 32 ) i [31:0] $end
$var integer 32 * out_file [31:0] $end
$scope module BCNN $end
$var wire 4 + bias_in [3:0] $end
$var wire 1 # clk_in $end
$var wire 9 , data_in [8:0] $end
$var wire 1 % reset_in $end
$var wire 9 - weight_in [8:0] $end
$var reg 1 . binarized_out $end
$var reg 1 ! data_out $end
$var reg 4 / population_count [3:0] $end
$var reg 5 0 true_sum [4:0] $end
$var integer 32 1 i [31:0] $end
$upscope $end
$upscope $end
$enddefinitions $end
#0
$dumpvars
bx 1
bx 0
bx /
x.
bx -
bx ,
bx +
b10 *
b0 )
b0 (
bx '
0&
1%
bx $
1#
bx "
x!
$end
#250
0!
0%
#500
b100 0
b100 /
b1001 1
1.
b1 )
b110011001 '
b110011001 -
b101001100 $
b101001100 ,
b101 "
b101 +
1%
0#
#1000
1!
1#
#1500
b1001 1
0.
b11010 0
b10 )
b100101001 '
b100101001 -
b111001111 $
b111001111 ,
b1011 "
b1011 +
0#
#2000
0!
1#
#2500
b1001 1
1.
b101 0
b11 )
b110011101 '
b110011101 -
b1001111 $
b1001111 ,
b110 "
b110 +
0#
#3000
1!
1#
#3500
b1001 1
b10 0
b100 )
b100011100 '
b100011100 -
b100100001 $
b100100001 ,
b11 "
b11 +
0#
#4000
1#
#4500
b1001 1
0.
b11010 0
b101 )
b1001111 '
b1001111 -
b111001 $
b111001 ,
b1011 "
b1011 +
0#
#5000
0!
1#
#5500
b1001 1
1.
b11 0
b110 )
b10110000 '
b10110000 -
b100100011 $
b100100011 ,
b100 "
b100 +
0#
#6000
1!
1#
#6500
b101 /
b1001 1
1.
b1 0
b111 )
b111101 '
b111101 -
b11101100 $
b11101100 ,
b0 "
b0 +
0#
#7000
1#
#7500
b110 /
b1001 1
0.
b11110 0
b1000 )
b10100010 '
b10100010 -
b11100001 $
b11100001 ,
b1011 "
b1011 +
0#
#8000
0!
1#
#8500
b101 /
b1001 1
b11101 0
b1001 )
b101011011 '
b101011011 -
b100010000 $
b100010000 ,
b1100 "
b1100 +
0#
#9000
1#
#9500
b100 /
b1001 1
1.
b0 0
b1010 )
b111010111 '
b111010111 -
b11111100 $
b11111100 ,
b1 "
b1 +
0#
#10000
1!
1#
#10500
b1001 1
0.
b11001 0
b1011 )
b110011101 '
b110011101 -
b101101001 $
b101101001 ,
b1010 "
b1010 +
0#
#11000
0!
1#
#11500
1.
b101 /
b1001 1
b0 0
b1100 )
b11000001 '
b11000001 -
b110001101 $
b110001101 ,
b1111 "
b1111 +
0#
#12000
1!
1#
#12500
b1000 /
b1001 1
0.
b11111 0
b1101 )
b101000011 '
b101000011 -
b111000011 $
b111000011 ,
b1000 "
b1000 +
0#
#13000
0!
1#
#13500
b110 /
b1001 1
1.
b11 0
b1110 )
b10111100 '
b10111100 -
b11011110 $
b11011110 ,
b0 "
b0 +
0#
#14000
1!
1#
#14500
b101 /
b1001 1
0.
b11100 0
b1111 )
b111011100 '
b111011100 -
b111101010 $
b111101010 ,
b1011 "
b1011 +
0#
#15000
0!
1#
#15500
b10 /
b1001 1
0.
b11100 0
b10000 )
b111010111 '
b111010111 -
b101101000 $
b101101000 ,
b1 "
b1 +
0#
#16000
1#
#16500
1.
b0 0
b100 /
b1001 1
b10001 )
b11000110 '
b11000110 -
b10100001 $
b10100001 ,
0#
#17000
1!
1#
#17500
b110 /
b1001 1
b1010 0
b10010 )
b10100101 '
b10100101 -
b11100011 $
b11100011 ,
b111 "
b111 +
0#
#18000
1#
#18500
b1001 1
b110 0
b10011 )
b101011110 '
b101011110 -
b100010100 $
b100010100 ,
b11 "
b11 +
0#
#19000
1#
#19500
b100 /
b1001 1
0.
b11000 0
b10100 )
b100100000 '
b100100000 -
b11010000 $
b11010000 ,
b1001 "
b1001 +
0#
#20000
0!
1#
#20500
b1001 1
b10111 0
b10101 )
b100111010 '
b100111010 -
b100000100 $
b100000100 ,
b1000 "
b1000 +
0#
#21000
1#
#21500
b101 /
b1001 1
b11010 0
b10110 )
b110001100 '
b110001100 -
b101011000 $
b101011000 ,
b1001 "
b1001 +
0#
#22000
1#
#22500
b1001 1
1.
b110 0
b10111 )
b101010110 '
b101010110 -
b100111100 $
b100111100 ,
b101 "
b101 +
0#
#23000
1!
1#
#23500
b100 /
b1001 1
0.
b10111 0
b11000 )
b111000011 '
b111000011 -
b110 $
b110 ,
b1000 "
b1000 +
0#
#24000
0!
1#
#24500
b11 /
b1001 1
1.
b10 0
b11001 )
b1000110 '
b1000110 -
b11001 $
b11001 ,
b101 "
b101 +
0#
#25000
1!
1#
#25500
b10 /
b1001 1
0.
b11001 0
b11010 )
b110111110 '
b110111110 -
b11001001 $
b11001001 ,
b1110 "
b1110 +
0#
#26000
0!
1#
#26500
1.
b100 /
b1001 1
b11 0
b11011 )
b10011010 '
b10011010 -
b110110111 $
b110110111 ,
b100 "
b100 +
0#
#27000
1!
1#
#27500
b11 /
b1001 1
0.
b11011 0
b11100 )
b101111 '
b101111 -
b111100100 $
b111100100 ,
b1110 "
b1110 +
0#
#28000
0!
1#
#28500
b101 /
b1001 1
1.
b101 0
b11101 )
b110110 '
b110110 -
b100100101 $
b100100101 ,
b100 "
b100 +
0#
#29000
1!
1#
#29500
b1001 1
b0 0
b11110 )
b101010100 '
b101010100 -
b100101100 $
b100101100 ,
b1111 "
b1111 +
0#
#30000
1#
#30500
b110 /
b1001 1
b100 0
b11111 )
b11111001 '
b11111001 -
b10110101 $
b10110101 ,
b1 "
b1 +
0#
#31000
1#
#31500
b100 /
b1001 1
b100 0
b100000 )
b10111 '
b10111 -
b110111110 $
b110111110 ,
b101 "
b101 +
0#
#32000
1#
#32500
b10 /
b1001 1
b1 0
b100001 )
b101100110 '
b101100110 -
b110001001 $
b110001001 ,
b110 "
b110 +
0#
#33000
1#
#33500
b100 /
b1001 1
0.
b10111 0
b100010 )
b111100 '
b111100 -
b100000110 $
b100000110 ,
b1000 "
b1000 +
0#
#34000
0!
1#
#34500
b1 /
b1001 1
b10011 0
b100011 )
b101010001 '
b101010001 -
b10111110 $
b10111110 ,
b1010 "
b1010 +
0#
#35000
1#
#35500
b100 /
b1001 1
b11000 0
b100100 )
b10010100 '
b10010100 -
b110100010 $
b110100010 ,
b1001 "
b1001 +
0#
#36000
1#
#36500
b1001 1
1.
b110 0
b100101 )
b10101111 '
b10101111 -
b101001011 $
b101001011 ,
b111 "
b111 +
0#
#37000
1!
1#
#37500
b110 /
b1001 1
b1000 0
b100110 )
b10100011 '
b10100011 -
b110101010 $
b110101010 ,
b101 "
b101 +
0#
#38000
1#
#38500
b100 /
b1001 1
0.
b11001 0
b100111 )
b101011100 '
b101011100 -
b0 $
b0 ,
b1010 "
b1010 +
0#
#39000
0!
1#
#39500
b1001 1
b11101 0
b101000 )
b100010011 '
b100010011 -
b110111000 $
b110111000 ,
b1110 "
b1110 +
0#
#40000
1#
#40500
b1001 1
b11110 0
b101001 )
b1111010 $
b1111010 ,
b1111 "
b1111 +
0#
#41000
1#
#41500
b11 /
b1001 1
0.
b11111 0
b101010 )
b101001 '
b101001 -
b11110111 $
b11110111 ,
b10 "
b10 +
0#
#42000
1#
#42500
1.
b110 /
b1001 1
b100 0
b101011 )
b111101011 '
b111101011 -
b110001010 $
b110001010 ,
b1 "
b1 +
0#
#43000
1!
1#
#43500
0.
b100 /
b1001 1
b11111 0
b101100 )
b100111101 '
b100111101 -
b111001100 $
b111001100 ,
b0 "
b0 +
0#
#44000
0!
1#
#44500
b1001 1
b10111 0
b101101 )
b101110001 '
b101110001 -
b100000100 $
b100000100 ,
b1000 "
b1000 +
0#
#45000
1#
#45500
b1001 1
b11111 0
b101110 )
b111101101 '
b111101101 -
b1111 $
b1111 ,
b0 "
b0 +
0#
#46000
1#
#46500
b11011 0
b10 /
b1001 1
b101111 )
b110100010 '
b110100010 -
b11011001 $
b11011001 ,
0#
#47000
1#
#47500
b110 /
b1001 1
1.
b1010 0
b110000 )
b1111111 '
b1111111 -
b101101011 $
b101101011 ,
b111 "
b111 +
0#
#48000
1!
1#
#48500
b110 0
b100 /
b1001 1
b110001 )
b101010 '
b101010 -
b101011000 $
b101011000 ,
0#
#49000
1#
#49500
b1001 1
0.
b11111 0
b110010 )
b110000000 '
b110000000 -
b1011000 $
b1011000 ,
b0 "
b0 +
0#
#50000
0!
1#
#50500
b101 /
b1001 1
1.
b100 0
b110011 )
b100110010 '
b100110010 -
b10010000 $
b10010000 ,
b11 "
b11 +
0#
#51000
1!
1#
#51500
b1001 1
b111 0
b110100 )
b101101001 '
b101101001 -
b11111000 $
b11111000 ,
b110 "
b110 +
0#
#52000
1#
#52500
b110 /
b1001 1
b100 0
b110101 )
b110111 '
b110111 -
b100100101 $
b100100101 ,
b1 "
b1 +
0#
#53000
1#
#53500
0.
b11 /
b1001 1
b11100 0
b110110 )
b100110110 '
b100110110 -
b10011101 $
b10011101 ,
b1111 "
b1111 +
0#
#54000
0!
1#
#54500
b101 /
b1001 1
1.
b1000 0
b110111 )
b100010100 '
b100010100 -
b101010011 $
b101010011 ,
b111 "
b111 +
0#
#55000
1!
1#
#55500
b110 /
b1001 1
0.
b11111 0
b111000 )
b10110011 '
b10110011 -
b100111011 $
b100111011 ,
b1100 "
b1100 +
0#
#56000
0!
1#
#56500
b11 /
b1001 1
1.
b0 0
b111001 )
b10010111 '
b10010111 -
b100000 $
b100000 ,
b11 "
b11 +
0#
#57000
1!
1#
#57500
b111 /
b1001 1
1.
b110 0
b111010 )
b100001010 '
b100001010 -
b1110 $
b1110 ,
b1 "
b1 +
0#
#58000
1#
#58500
0.
b100 /
b1001 1
b11100 0
b111011 )
b1000000 '
b1000000 -
b110011 $
b110011 ,
b1101 "
b1101 +
0#
#59000
0!
1#
#59500
b1001 1
1.
b0 0
b111100 )
b101011000 '
b101011000 -
b10110000 $
b10110000 ,
b1 "
b1 +
0#
#60000
1!
1#
#60500
b1001 1
0.
b11010 0
b111101 )
b10101001 '
b10101001 -
b100000101 $
b100000101 ,
b1011 "
b1011 +
0#
#61000
0!
1#
#61500
b1001 1
b111110 )
b100000100 '
b100000100 -
b1001001 $
b1001001 ,
0#
#62000
1#
#62500
b101 /
b1001 1
1.
b100 0
b111111 )
b111001011 '
b111001011 -
b111010110 $
b111010110 ,
b11 "
b11 +
0#
#63000
1!
1#
#63500
b100 /
b1001 1
b1 0
b1000000 )
b11101011 '
b11101011 -
b10100100 $
b10100100 ,
b10 "
b10 +
0#
#64000
1#
#64500
b101 /
b1001 1
0.
b11010 0
b1000001 )
b110110110 '
b110110110 -
b101010100 $
b101010100 ,
b1001 "
b1001 +
0#
#65000
0!
1#
#65500
b11 /
b1001 1
0.
b11110 0
b1000010 )
b110000010 '
b110000010 -
b111011 $
b111011 ,
b1 "
b1 +
0#
#66000
1#
#66500
b10 /
b1001 1
b10100 0
b1000011 )
b1110111 $
b1110111 ,
b1001 "
b1001 +
0#
#67000
1#
#67500
b101 /
b1001 1
1.
b110 0
b1000100 )
b101011100 '
b101011100 -
b111000 $
b111000 ,
b101 "
b101 +
0#
#68000
1!
1#
#68500
b11 /
b1001 1
b100 0
b1000101 )
b1011100 '
b1011100 -
b10100000 $
b10100000 ,
b111 "
b111 +
0#
#69000
1#
#69500
b100 /
b1001 1
0.
b11101 0
b1000110 )
b100000001 '
b100000001 -
b10101101 $
b10101101 ,
b1110 "
b1110 +
0#
#70000
0!
1#
#70500
b101 /
b1001 1
b11101 0
b1000111 )
b101010111 '
b101010111 -
b100011100 $
b100011100 ,
b1100 "
b1100 +
0#
#71000
1#
#71500
b1001 1
1.
b111 0
b1001000 )
b110000101 '
b110000101 -
b100110111 $
b100110111 ,
b110 "
b110 +
0#
#72000
1!
1#
#72500
0.
b10 /
b1001 1
b11100 0
b1001001 )
b1110111 '
b1110111 -
b100011000 $
b100011000 ,
b1 "
b1 +
0#
#73000
0!
1#
#73500
b101 /
b1001 1
b11001 0
b1001010 )
b101010010 '
b101010010 -
b111110111 $
b111110111 ,
b1000 "
b1000 +
0#
#74000
1#
#74500
1.
b110 /
b1001 1
b0 0
b1001011 )
b100110011 '
b100110011 -
b100100101 $
b100100101 ,
b1101 "
b1101 +
0#
#75000
1!
1#
#75500
b100 /
b1001 1
b110 0
b1001100 )
b101010000 '
b101010000 -
b111111011 $
b111111011 ,
b111 "
b111 +
0#
#76000
1#
#76500
b11 /
b1001 1
0.
b11100 0
b1001101 )
b110000 '
b110000 -
b1001011 $
b1001011 ,
b1111 "
b1111 +
0#
#77000
0!
1#
#77500
b101 /
b1001 1
1.
b1000 0
b1001110 )
b101011001 '
b101011001 -
b101000100 $
b101000100 ,
b111 "
b111 +
0#
#78000
1!
1#
#78500
b100 /
b1001 1
0.
b11000 0
b1001111 )
b100001000 '
b100001000 -
b10110 $
b10110 ,
b1001 "
b1001 +
0#
#79000
0!
1#
#79500
b101 /
b1001 1
1.
b1000 0
b1010000 )
b11000101 '
b11000101 -
b10001011 $
b10001011 ,
b111 "
b111 +
0#
#80000
1!
1#
#80500
b11 /
b1001 1
0.
b10110 0
b1010001 )
b110011001 '
b110011001 -
b111100010 $
b111100010 ,
b1001 "
b1001 +
0#
#81000
0!
1#
#81500
b101 /
b1001 1
1.
b110 0
b1010010 )
b101000010 '
b101000010 -
b100101000 $
b100101000 ,
b101 "
b101 +
0#
#82000
1!
1#
#82500
b1001 1
0.
b11101 0
b1010011 )
b110110010 '
b110110010 -
b110011001 $
b110011001 ,
b1100 "
b1100 +
0#
#83000
0!
1#
#83500
b111 /
b1001 1
1.
b101 0
b1010100 )
b110110 '
b110110 -
b11110 $
b11110 ,
b0 "
b0 +
0#
#84000
1!
1#
#84500
0.
b100 /
b1001 1
b11011 0
b1010101 )
b1111111 '
b1111111 -
b11010100 $
b11010100 ,
b1100 "
b1100 +
0#
#85000
0!
1#
#85500
b1001 1
1.
b101 0
b1010110 )
b100101100 '
b100101100 -
b11110100 $
b11110100 ,
b110 "
b110 +
0#
#86000
1!
1#
#86500
b101 /
b1001 1
1.
b0 0
b1010111 )
b110111010 '
b110111010 -
b100010011 $
b100010011 ,
b1111 "
b1111 +
0#
#87000
1#
#87500
b110 /
b1001 1
1.
b0 0
b1011000 )
b10001101 '
b10001101 -
b10010100 $
b10010100 ,
b1101 "
b1101 +
0#
#88000
1#
#88500
b100 /
b1001 1
0.
b10111 0
b1011001 )
b11001101 '
b11001101 -
b100111 $
b100111 ,
b1000 "
b1000 +
0#
#89000
0!
1#
#89500
1.
b1000 /
b1001 1
b101 0
b1011010 )
b110110100 '
b110110100 -
b110110000 $
b110110000 ,
b1110 "
b1110 +
0#
#90000
1!
1#
#90500
b100 /
b1001 1
0.
b10111 0
b1011011 )
b10000001 '
b10000001 -
b111000110 $
b111000110 ,
b1000 "
b1000 +
0#
#91000
0!
1#
#91500
b11 /
b1001 1
b11001 0
b1011100 )
b1011000 '
b1011000 -
b10100001 $
b10100001 ,
b1100 "
b1100 +
0#
#92000
1#
#92500
1.
b1000 /
b1001 1
b1001 0
b1011101 )
b110110100 '
b110110100 -
b10110100 $
b10110100 ,
b10 "
b10 +
0#
#93000
1!
1#
#93500
0.
b100 /
b1001 1
b11001 0
b1011110 )
b111000110 '
b111000110 -
b100111 $
b100111 ,
b1010 "
b1010 +
0#
#94000
0!
1#
#94500
b110 /
b1001 1
b11110 0
b1011111 )
b1011010 '
b1011010 -
b100111010 $
b100111010 ,
b1011 "
b1011 +
0#
#95000
1#
#95500
b11000 0
b11 /
b1001 1
b1100000 )
b110000101 '
b110000101 -
b101111001 $
b101111001 ,
0#
#96000
1#
#96500
b110 /
b1001 1
1.
b110 0
b1100001 )
b11010111 '
b11010111 -
b1000101 $
b1000101 ,
b11 "
b11 +
0#
#97000
1!
1#
#97500
b101 /
b1001 1
0.
b11100 0
b1100010 )
b1000101 '
b1000101 -
b111100100 $
b111100100 ,
b1011 "
b1011 +
0#
#98000
0!
1#
#98500
b11 /
b1001 1
1.
b0 0
b1100011 )
b11111010 '
b11111010 -
b11000101 $
b11000101 ,
b11 "
b11 +
0#
#99000
1!
1#
#99500
b10 0
b100 /
b1001 1
b1100100 )
b101000001 '
b101000001 -
b111110010 $
b111110010 ,
0#
#100000
1#
#100500
b1100101 )
0#
#101000
1&
1#
